setup.py
withings_cli/__init__.py
withings_cli/cli.py
withings_cli/config.py
withings_cli.egg-info/PKG-INFO
withings_cli.egg-info/SOURCES.txt
withings_cli.egg-info/dependency_links.txt
withings_cli.egg-info/entry_points.txt
withings_cli.egg-info/requires.txt
withings_cli.egg-info/top_level.txt