Metadata-Version: 1.1
Name: withings-cli
Version: 0.3
Summary: A Command-line interface for Withings API
Home-page: https://github.com/kblomqvist/withings-cli
Author: Kim Blomqvist
Author-email: kblomqvist@iki.fi
License: MIT
Download-URL: https://github.com/kblomqvist/withings-cli/tarball/0.3
Keywords: withings,cli-utilities
Platform: UNKNOWN
Classifier: Programming Language :: Python :: 2.7
Classifier: Programming Language :: Python :: 3.6
Classifier: License :: OSI Approved :: MIT License
